django_ninja_jwt_basic/__init__.py
django_ninja_jwt_basic/api.py
django_ninja_jwt_basic/apps.py
django_ninja_jwt_basic/security.py
django_ninja_jwt_basic-0.1.2.dist-info/LICENSE
django_ninja_jwt_basic-0.1.2.dist-info/METADATA
django_ninja_jwt_basic-0.1.2.dist-info/WHEEL
django_ninja_jwt_basic-0.1.2.dist-info/RECORD
