Metadata-Version: 2.1
Name: django-ninja-jwt-basic
Version: 0.1.2
Summary: Simple JWT-based authentication designed for Django and Django Ninja. This package aims to provide a minimalistic approach to JWT authentication with the least amount of dependencies, making it easy to integrate and use in your projects.
Home-page: https://github.com/SpaceShaman/django-ninja-jwt-basic
License: MIT
Author: SpaceShaman
Author-email: spaceshaman@tuta.io
Requires-Python: >=3.10.0,<4.0.0
Classifier: Framework :: Django
Classifier: Framework :: Django :: 4.2
Classifier: Framework :: Django :: 5.0
Classifier: Framework :: Django :: 5.1
Classifier: License :: OSI Approved :: MIT License
Classifier: Programming Language :: Python :: 3
Classifier: Programming Language :: Python :: 3.10
Classifier: Programming Language :: Python :: 3.11
Classifier: Programming Language :: Python :: 3.12
Requires-Dist: django (>4.2.14,<6.0.0)
Requires-Dist: django-ninja (>=1.2.1,<2.0.0)
Requires-Dist: pyjwt (>=2.8.0,<3.0.0)
Project-URL: Repository, https://github.com/SpaceShaman/django-ninja-jwt-basic
